MANIFEST.in
README.md
setup.py
cute_mongo_forms/__init__.py
cute_mongo_forms/qt.py
cute_mongo_forms/template.py
cute_mongo_forms/test.py
cute_mongo_forms/tools.py
cute_mongo_forms/version.py
cute_mongo_forms.egg-info/PKG-INFO
cute_mongo_forms.egg-info/SOURCES.txt
cute_mongo_forms.egg-info/dependency_links.txt
cute_mongo_forms.egg-info/requires.txt
cute_mongo_forms.egg-info/top_level.txt
cute_mongo_forms/column/__init__.py
cute_mongo_forms/column/base.py
cute_mongo_forms/column/constant.py
cute_mongo_forms/column/numeric.py
cute_mongo_forms/column/string.py
cute_mongo_forms/container/__init__.py
cute_mongo_forms/container/base.py
cute_mongo_forms/container/editform.py
cute_mongo_forms/data/some_auxiliary_file
cute_mongo_forms/db/__init__.py
cute_mongo_forms/db/base.py
cute_mongo_forms/db/mongo.py
cute_mongo_forms/db/simple.py
cute_mongo_forms/example/__init__.py
cute_mongo_forms/example/datamodel.py
cute_mongo_forms/example/gui.py
cute_mongo_forms/example/test.py
cute_mongo_forms/row/__init__.py
cute_mongo_forms/row/base.py
docs/.nojekyll
docs/Makefile
docs/authors.rst
docs/clean.bash
docs/compile.bash
docs/conf.py
docs/example.rst
docs/examples.rst
docs/fix_rst.py
docs/home.md
docs/index.html
docs/index.rst
docs/intro.rst
docs/lesson_1.rst
docs/lesson_2.rst
docs/lesson_3.rst
docs/lesson_4.rst
docs/lesson_5.rst
docs/lesson_6.rst
docs/lesson_7.rst
docs/lesson_8.rst
docs/license.rst
docs/requirements.rst
docs/submodules.rst
docs/tutorial.rst
docs/tutorial.save.rst
docs/tutorial_epi.rst
docs/tutorial_intro.rst
docs/_build/doctrees/authors.doctree
docs/_build/doctrees/environment.pickle
docs/_build/doctrees/example.doctree
docs/_build/doctrees/examples.doctree
docs/_build/doctrees/index.doctree
docs/_build/doctrees/intro.doctree
docs/_build/doctrees/lesson_1.doctree
docs/_build/doctrees/lesson_2.doctree
docs/_build/doctrees/lesson_3.doctree
docs/_build/doctrees/lesson_4.doctree
docs/_build/doctrees/lesson_5.doctree
docs/_build/doctrees/lesson_6.doctree
docs/_build/doctrees/lesson_7.doctree
docs/_build/doctrees/lesson_8.doctree
docs/_build/doctrees/license.doctree
docs/_build/doctrees/requirements.doctree
docs/_build/doctrees/submodules.doctree
