Metadata-Version: 2.1
Name: cute-mongo-forms
Version: 0.7.4
Summary: Document database / Qt Widget integration
Home-page: https://elsampsa.github.io/cute_mongo_forms/
Author: Sampsa Riikonen
Author-email: sampsa.riikonen@iki.fi
License: LGPLv3+
Keywords: qt mongo
Platform: UNKNOWN
Classifier: Development Status :: 4 - Beta
Classifier: Intended Audience :: Developers
Classifier: Operating System :: POSIX :: Linux
Classifier: Topic :: Database
Classifier: License :: OSI Approved :: GNU Lesser General Public License v3 or later (LGPLv3+)
Classifier: Programming Language :: Python :: 3
